{
  "Ambala": [
    {
      "name": "John Doe",
      "displayimg": "https://res.cloudinary.com/djp1oiwpe/image/upload/v1776928926/f3uigw9rbgjamj1vz0wz.jpg",
      "certificate": [],
      "location": "Ambala",
      "shortdescription": "no",
      "price": 0,
      "rating": 0,
      "ownername": "John Doe",
      "allimg": [],
      "fulldescription": "",
      "skills": [],
      "summary": "",
      "noofpetswatched": "",
      "petsize": [],
      "pottybreaks": "",
      "typeOfHome": "",
      "Emergencytransport": "",
      "petTypeAccepted": [],
      "bookings": [],
      "phoneNumber": "07973951757",
      "email": "john@example.com",
      "userid": "638fc2f4-964b-461d-a70d-4af052e79b25",
      "crecheid": "",
      "username": "john12345"
    },
    {
      "name": "John Doe",
      "displayimg": "https://res.cloudinary.com/djp1oiwpe/image/upload/v1776972107/zbcpevugv8vm8eiziynl.jpg",
      "certificate": [],
      "location": "Ambala",
      "shortdescription": "no",
      "price": 0,
      "rating": 0,
      "ownername": "John Doe",
      "allimg": [],
      "fulldescription": "",
      "skills": [],
      "summary": "",
      "noofpetswatched": "",
      "petsize": [],
      "pottybreaks": "",
      "typeOfHome": "",
      "Emergencytransport": "",
      "petTypeAccepted": [],
      "bookings": [],
      "phoneNumber": "07973951757",
      "email": "john@example.com",
      "userid": "638fc2f4-964b-461d-a70d-4af052e79b25",
      "crecheid": "ae671d31-f9ef-4cd2-9f44-cc2adb4974e3",
      "username": "john12345"
    },
    {
      "name": "John Doe",
      "displayimg": "https://res.cloudinary.com/djp1oiwpe/image/upload/v1777002365/ddjcepnehgclt9yxatt5.jpg",
      "certificate": [],
      "location": "Ambala",
      "shortdescription": "no",
      "price": 0,
      "rating": 0,
      "ownername": "John Doe",
      "allimg": [],
      "fulldescription": "",
      "skills": [],
      "summary": "",
      "noofpetswatched": "",
      "petsize": [],
      "pottybreaks": "",
      "typeOfHome": "",
      "Emergencytransport": "",
      "petTypeAccepted": [],
      "bookings": [],
      "phoneNumber": "07973951757",
      "email": "john@example.com",
      "userid": "638fc2f4-964b-461d-a70d-4af052e79b25",
      "crecheid": "c50be172-7d8e-4eb9-bb0a-793aaa4fb249",
      "username": "john12345"
    }
  ],
  "Panipat": [
    {
      "name": "John Doe",
      "displayimg": "https://res.cloudinary.com/djp1oiwpe/image/upload/v1777002410/kd5t2kryxygd6670pzry.jpg",
      "certificate": [],
      "location": "Panipat",
      "shortdescription": "no",
      "price": 0,
      "rating": 0,
      "ownername": "John Doe",
      "allimg": [],
      "fulldescription": "",
      "skills": [],
      "summary": "",
      "noofpetswatched": "",
      "petsize": [],
      "pottybreaks": "",
      "typeOfHome": "",
      "Emergencytransport": "",
      "petTypeAccepted": [],
      "bookings": [],
      "phoneNumber": "07973951757",
      "email": "john@example.com",
      "userid": "638fc2f4-964b-461d-a70d-4af052e79b25",
      "crecheid": "a5967fcf-21bf-46c2-933b-28a26e7cd9d2",
      "username": "john12345"
    }
  ],
  "Yamunanagar": [
    {
      "name": "Test User",
      "displayimg": "https://res.cloudinary.com/djp1oiwpe/image/upload/v1777002513/dlpvrl377nnp7gfeupx2.jpg",
      "certificate": [],
      "location": "Yamunanagar",
      "shortdescription": "no",
      "price": 0,
      "rating": 0,
      "ownername": "test",
      "allimg": [],
      "fulldescription": "",
      "skills": [],
      "summary": "",
      "noofpetswatched": "",
      "petsize": [],
      "pottybreaks": "",
      "typeOfHome": "",
      "Emergencytransport": "",
      "petTypeAccepted": [],
      "bookings": [],
      "phoneNumber": "07973951757",
      "email": "test@example.com",
      "userid": "638fc2f4-964b-461d-a70d-4af052e79b25",
      "crecheid": "c3bdcccb-1ac9-4230-b9d1-e60f69d2bce8",
      "username": "john12345"
    }
  ],
  "Rohtak": [
    {
      "name": "Random user",
      "displayimg": "https://res.cloudinary.com/djp1oiwpe/image/upload/v1777003356/dpqbjsllzxnpnjdem2t7.jpg",
      "certificate": [],
      "location": "Rohtak",
      "shortdescription": "no",
      "price": 0,
      "rating": 0,
      "ownername": "Random",
      "allimg": [],
      "fulldescription": "",
      "skills": [],
      "summary": "",
      "noofpetswatched": "",
      "petsize": [],
      "pottybreaks": "",
      "typeOfHome": "",
      "Emergencytransport": "",
      "petTypeAccepted": [],
      "bookings": [],
      "phoneNumber": "07973951757",
      "email": "Random@example.com",
      "userid": "638fc2f4-964b-461d-a70d-4af052e79b25",
      "crecheid": "16fe1069-93c9-4bad-97e5-30a6dfc520a8",
      "username": "john12345"
    }
  ],
  "Karnal": [
    {
      "name": "John Doe",
      "displayimg": "https://res.cloudinary.com/djp1oiwpe/image/upload/v1777003671/ca9dpmsverz67jciclkm.jpg",
      "certificate": [],
      "location": "Karnal",
      "shortdescription": "no",
      "price": 0,
      "rating": 0,
      "ownername": "John Doe",
      "allimg": [],
      "fulldescription": "",
      "skills": [],
      "summary": "",
      "noofpetswatched": "",
      "petsize": [],
      "pottybreaks": "",
      "typeOfHome": "",
      "Emergencytransport": "",
      "petTypeAccepted": [],
      "bookings": [],
      "phoneNumber": "07973951757",
      "email": "john@example.com",
      "userid": "638fc2f4-964b-461d-a70d-4af052e79b25",
      "crecheid": "ac02696e-32be-4467-83a0-717df66e406f",
      "username": "john12345"
    }
  ],
  "Faridabad": [
    {
      "name": "John Doe",
      "displayimg": "https://res.cloudinary.com/djp1oiwpe/image/upload/v1777113902/qmlw4yqir15qwmha7btb.jpg",
      "certificate": [
        "https://res.cloudinary.com/djp1oiwpe/image/upload/v1777113903/a8btveo2sgqoe1iitqjz.webp"
      ],
      "location": "Faridabad",
      "shortdescription": "no",
      "price": 3500,
      "rating": 0,
      "ownername": "John Doe",
      "allimg": [
        "https://res.cloudinary.com/djp1oiwpe/image/upload/v1777113902/k7rbfxybtuiiee17pcfo.jpg"
      ],
      "fulldescription": "",
      "skills": [
        "Dog Walking"
      ],
      "summary": "",
      "noofpetswatched": "2",
      "petsize": [
        {
          "src": "icon_03.png",
          "weight": "10-20kg"
        }
      ],
      "pottybreaks": "2",
      "typeOfHome": "house",
      "Emergencytransport": "",
      "petTypeAccepted": [
        "Dog"
      ],
      "bookings": [],
      "phoneNumber": "07973951757",
      "email": "john@example.com",
      "userid": "95c869a4-ab35-4956-b264-0681f67895c6",
      "crecheid": "12ed4e34-9caf-4ab4-9b44-fb85725d5a91",
      "username": "john123"
    }
  ]
}